API.md
CHANGES.md
LICENSE.md
MANIFEST.in
README.md
VERSION
pyproject.toml
requirements-ci.txt
requirements-docs.txt
requirements.txt
setup.py
bin/radical-analytics-check
bin/radical-analytics-inspect
bin/radical-analytics-parse-profile.py
bin/radical-analytics-plot.py
bin/radical-analytics-version
bin/radical-analytics-wrangler-vivek.py
bin/radical-analytics-wrangler.py
bin/rp_inspect/plot_conc.py
bin/rp_inspect/plot_dur.py
bin/rp_inspect/plot_rate.py
bin/rp_inspect/plot_state.py
bin/rp_inspect/plot_util.py
bin/rp_inspect/plot_util_2.py
docs/source/README.md
docs/source/metrics.md
examples/00_session_describe_rp.py
examples/01_session_list_rp.py
examples/02_session_get_rp.py
examples/03_session_filter_rp.py
examples/04_session_duration_rp.py
examples/05_relationsships.py
examples/06_events.py
examples/06_ra_events.py
examples/07_event_timeline.py
examples/08_core_utilization_plot.py
examples/08c_core_utilization_plot.py
examples/09_session_plots.py
examples/10_durations.py
examples/multi_session.py
src/radical.analytics.egg-info/PKG-INFO
src/radical.analytics.egg-info/SOURCES.txt
src/radical.analytics.egg-info/dependency_links.txt
src/radical.analytics.egg-info/not-zip-safe
src/radical.analytics.egg-info/requires.txt
src/radical.analytics.egg-info/top_level.txt
src/radical/analytics/VERSION
src/radical/analytics/__init__.py
src/radical/analytics/entity.py
src/radical/analytics/experiment.py
src/radical/analytics/plotter.py
src/radical/analytics/session.py
src/radical/analytics/utils/__init__.py
src/radical/analytics/utils/plot.py
styles/radical_mpl.txt
tests/test_duration_method.py
tests/test_entity.py
tests/test_session.py